kano/dataset_utils.py
kano/detect_utils.py
kano/file_utils.py
kano/pose_utils.py
kano/segment_utils.py
kano/video_utils.py
kano_cv-3.6.2.dist-info/LICENSE
kano_cv-3.6.2.dist-info/METADATA
kano_cv-3.6.2.dist-info/WHEEL
kano_cv-3.6.2.dist-info/top_level.txt
kano_cv-3.6.2.dist-info/RECORD
