Metadata-Version: 2.1
Name: kano-cv
Version: 3.6.2
Summary: Helpful functions for Computer Vision tasks
Author-email: egliette <leminhtu74@gmail.com>
License: MIT
Project-URL: Github, https://github.com/egliette/kano
Keywords: computer vision
Classifier: License :: OSI Approved :: MIT License
Classifier: Programming Language :: Python :: 3
Requires-Python: >=3.9
License-File: LICENSE
Requires-Dist: tqdm>=4.8
Requires-Dist: numpy>=1.23
Requires-Dist: psutil>=5.0
Requires-Dist: pandas>=2.0
Requires-Dist: opencv-python>=4.9
Provides-Extra: dev
Requires-Dist: black>=24.2.0; extra == "dev"
Requires-Dist: isort>=5.13.2; extra == "dev"
Requires-Dist: flake8>=7.0.0; extra == "dev"
Requires-Dist: pip-tools>=7.3.0; extra == "dev"
Requires-Dist: pytest>=8.0.0; extra == "dev"
Requires-Dist: build>=1.0.3; extra == "dev"
Requires-Dist: twine>=5.0.0; extra == "dev"
Requires-Dist: pre-commit>=3.6.1; extra == "dev"
Requires-Dist: python-semantic-release>=9.1.0; extra == "dev"
